Metadata-Version: 1.0
Name: distributions-binomial-dega
Version: 1.1
Summary: Gaussian and Binomial distributions
Home-page: UNKNOWN
Author: Sverige Gewoon
Author-email: sverige.gewoon@pass.com
License: UNKNOWN
Platform: UNKNOWN
